{
  "tokens": [],
  "pathMap": {
    "/home/jlarky.guest/work": "/Users/jlarky/work"
  },
  "allow": {
    "*": [
      "gh pr view *",
      "gh pr list *",
      [
        "gh",
        "api",
        {
          "regexp": "^repos/[A-Za-z0-9-]+/[A-Za-z0-9._-]+/pulls/[0-9]+/(comments|reviews|review_comments)$"
        }
      ],
      "gh issue view *",
      "gh issue list *",
      "git status",
      "git log *",
      "git diff *"
    ],
    "/home/user/full-vibes": [
      "git push -f",
      "git push *"
    ]
  },
  "deny": {
    "*": [
      "git push -f"
    ],
    "/home/user/prod-infra": [
      "git *"
    ]
  }
}
